zotero_qa_notes/__init__.py
zotero_qa_notes/cli.py
zotero_qa_notes/converter.py
zotero_qa_notes-0.1.0.dist-info/licenses/LICENSE
zotero_qa_notes-0.1.0.dist-info/METADATA
zotero_qa_notes-0.1.0.dist-info/WHEEL
zotero_qa_notes-0.1.0.dist-info/entry_points.txt
zotero_qa_notes-0.1.0.dist-info/top_level.txt
zotero_qa_notes-0.1.0.dist-info/RECORD
