Metadata-Version: 2.4
Name: zotero-qa-notes
Version: 0.1.0
Summary: Convert Zotero JSON export into Markdown with optional Q&A prompts
Author-email: innoxmind <innoxmind@gmail.com>
License: MIT
Requires-Python: >=3.9
License-File: LICENSE
Requires-Dist: markdownify>=0.14.1
Requires-Dist: python-slugify>=8.0.4
Dynamic: license-file
